stac_fastapi/mongo/__init__.py
stac_fastapi/mongo/app.py
stac_fastapi/mongo/config.py
stac_fastapi/mongo/core.py
stac_fastapi/mongo/serializers.py
stac_fastapi/mongo/session.py
stac_fastapi/mongo/transactions.py
stac_fastapi/mongo/version.py
stac_fastapi/mongo/extensions/__init__.py
stac_fastapi/mongo/extensions/query.py
stac_fastapi/mongo/models/__init__.py
stac_fastapi/mongo/models/search.py
stac_fastapi/mongo/types/error_checks.py
stac_fastapi/mongo/types/search.py
tests/api/__init__.py
tests/api/test_api.py
tests/clients/__init__.py
tests/clients/test_mongo.py
tests/features/__init__.py
tests/features/test_custom_models.py
tests/resources/__init__.py
tests/resources/test_collection.py
tests/resources/test_conformance.py
tests/resources/test_item.py
tests/resources/test_mgmt.py
stac_fastapi.nosql.mongo-2.3.0.dist-info/METADATA
stac_fastapi.nosql.mongo-2.3.0.dist-info/WHEEL
stac_fastapi.nosql.mongo-2.3.0.dist-info/entry_points.txt
stac_fastapi.nosql.mongo-2.3.0.dist-info/top_level.txt
stac_fastapi.nosql.mongo-2.3.0.dist-info/RECORD
