Metadata-Version: 2.1
Name: stac-fastapi.nosql.mongo
Version: 2.3.0
Summary: An implementation of STAC API based on the FastAPI framework.
Home-page: https://github.com/jonhealy1/stac-fastapi-nosql
Author: Arturo Engineering
Author-email: engineering@arturo.ai
License: MIT
Keywords: STAC FastAPI COG
Platform: UNKNOWN
Classifier: Intended Audience :: Developers
Classifier: Intended Audience :: Information Technology
Classifier: Intended Audience :: Science/Research
Classifier: Programming Language :: Python :: 3.8
Classifier: License :: OSI Approved :: MIT License
Requires-Python: >=3.8
Requires-Dist: attrs
Requires-Dist: pydantic[dotenv]
Requires-Dist: stac-pydantic (==2.0.*)
Requires-Dist: stac-fastapi.types (==2.3.0)
Requires-Dist: stac-fastapi.api (==2.3.0)
Requires-Dist: stac-fastapi.extensions (==2.3.0)
Requires-Dist: fastapi-utils
Requires-Dist: pymongo
Requires-Dist: pystac[validation]
Requires-Dist: uvicorn
Provides-Extra: dev
Requires-Dist: pytest ; extra == 'dev'
Requires-Dist: pytest-cov ; extra == 'dev'
Requires-Dist: pytest-asyncio ; extra == 'dev'
Requires-Dist: pre-commit ; extra == 'dev'
Requires-Dist: requests ; extra == 'dev'
Provides-Extra: docs
Requires-Dist: mkdocs ; extra == 'docs'
Requires-Dist: mkdocs-material ; extra == 'docs'
Requires-Dist: pdocs ; extra == 'docs'
Provides-Extra: server
Requires-Dist: uvicorn[standard] (<0.14.0,>=0.12.0) ; extra == 'server'
